{
    "id": "magical-glass-s",
    "name": "Magical Glass",
    "subtitle": "...What fucking game am I playing again?",

    "version": "v4.2.0",
    "engineVer": "v0.9.0-dev",

    "chapter": 2,

    "encounter": "dummy",

    "map": "tundra3",

    "party": ["kris"],

    "inventory": {
        "items": ["items/monster_candy", "items/spider_donut", "items/spider_cider", "items/butterscotch_pie", "armors/bandage_ut", "weapons/empty_gun"],
        "box_a": ["weapons/tough_glove"],
        "key_items": ["cell_phone"]
    },

    "equipment": {
        "kris": {
            "weapon": "weapons/stick",
            "armor": ["armors/bandage_ut"]
        }
    },

    "config": {
        "kristal": {
            "mercyBar": false,
            "mercyMessages": false,
            "enemyBarPercentages": false,
            "smallSaveMenu": false
            // End of config
        }
    }
}